llama_index/indices/managed/llama_cloud/__init__.py
llama_index/indices/managed/llama_cloud/api_utils.py
llama_index/indices/managed/llama_cloud/base.py
llama_index/indices/managed/llama_cloud/composite_retriever.py
llama_index/indices/managed/llama_cloud/retriever.py
llama_index_indices_managed_llama_cloud-0.9.3.dist-info/METADATA
llama_index_indices_managed_llama_cloud-0.9.3.dist-info/WHEEL
llama_index_indices_managed_llama_cloud-0.9.3.dist-info/licenses/LICENSE
llama_index_indices_managed_llama_cloud-0.9.3.dist-info/RECORD
