Metadata-Version: 2.4
Name: llama-index-indices-managed-llama-cloud
Version: 0.9.3
Summary: llama-index indices llama-cloud integration
Author-email: Logan Markewich <logan@llamaindex.ai>
License-Expression: MIT
License-File: LICENSE
Requires-Python: <4.0,>=3.9
Requires-Dist: deprecated==1.2.18
Requires-Dist: llama-cloud==0.1.35
Requires-Dist: llama-index-core<0.14,>=0.13.0
